MNIF/__init__.py
MNIF/mnif.py
mnif-0.0.1.dist-info/LICENSE.txt
mnif-0.0.1.dist-info/METADATA
mnif-0.0.1.dist-info/WHEEL
mnif-0.0.1.dist-info/top_level.txt
mnif-0.0.1.dist-info/RECORD
