Metadata-Version: 2.1
Name: mnif
Version: 0.0.1
Summary: A Package That Converts Mixed Numbers To Improper Fractions And Vice Versa
Home-page: https://github.com/TechGuru9000/mnif/tree/main
Author: Blazing MarshMello
Author-email: srilalithansuresh@gmail.com
License: UNKNOWN
Project-URL: Bug Tracker, https://github.com/pypa/sampleproject/issues
Platform: UNKNOWN
Classifier: Programming Language :: Python :: 3
Classifier: License :: OSI Approved :: MIT License
Classifier: Operating System :: OS Independent
Requires-Python: >=3.6
